EJERCICIO 3/ejercicio3.v
module FFP1(input wire clk, reset, enable, A, output reg Y);
 always @ (posedge clk or posedge reset) begin
    if (reset)
      Y <= 1'b0;
    else if(enable)
      Y <= A;
  end
endmodule

module FFPJK(input wire clk, reset, enable, J, K, output wire Y);
  wire N1, N2, A1, A2, O1;
  not(N1, K);
  not(N2, Y);
  and(A1, Y, N1);
  and(A2, N2, J);
  or(O1, A1, A2);
  FFP1 U1(clk, reset, enable, O1, Y);
endmodule

EJERCICIO 3/ejercicio3_tb.v
module testbench();
reg clk, reset, enable, J, K;
wire Y;
FFPJK U1(clk, reset, enable, J, K, Y);

always
  #1 clk <= ~clk;

initial begin
  $display("FLIP FLOP TIPO JK");
  $display("clk reset, enable A | Y");
  $display("-----------|---------");
  $monitor("%b %b %b %b %b |  %b", clk, reset, enable, J, K, Y);
    clk = 0; reset = 0; enable = 0; J = 0; K = 0;
  #1 clk = 0; reset = 1; enable = 0; J = 0; K = 0;
  #1 reset = 0; enable = 1; J = 0; K = 0;
  #1 reset = 0; enable = 1; J = 0; K = 0;
  #1 reset = 0; enable = 1; J = 1; K = 0;
  #1 reset = 0; enable = 1; J = 1; K = 0;
  #1 reset = 0; enable = 1; J = 0; K = 1;
  #1 reset = 0; enable = 1; J = 0; K = 1;
  #1 reset = 0; enable = 1; J = 1; K = 1;
  #1 reset = 0; enable = 1; J = 1; K = 1;
  #1 reset = 0; enable = 1; J = 0; K = 0;
end

initial
#18 $finish;
initial begin
  $dumpfile("ejercicio3_tb.vcd");
  $dumpvars(0, testbench);
end
endmodule

EJERCICIO 3/ejercicio3_tb.vcd
$date
	Sat Oct 31 01:11:04 2020
$end
$version
	Icarus Verilog
$end
$timescale
	1ps
$end
$scope module testbench $end
$var wire 1 ! Y $end
$var reg 1 " J $end
$var reg 1 # K $end
$var reg 1 $ clk $end
$var reg 1 % enable $end
$var reg 1 & reset $end
$scope module U1 $end
$var wire 1 ' A1 $end
$var wire 1 ( A2 $end
$var wire 1 " J $end
$var wire 1 # K $end
$var wire 1 ) N1 $end
$var wire 1 * N2 $end
$var wire 1 + O1 $end
$var wire 1 $ clk $end
$var wire 1 % enable $end
$var wire 1 & reset $end
$var wire 1 ! Y $end
$scope module U1 $end
$var wire 1 + A $end
$var wire 1 $ clk $end
$var wire 1 % enable $end
$var wire 1 & reset $end
$var reg 1 ! Y $end
$upscope $end
$upscope $end
$upscope $end
$enddefinitions $end
#0
$dumpvars
x+
x*
1)
0(
x'
0&
0%
0$
0#
0"
x!
$end
#1
0+
0'
1*
0!
1$
1&
#2
0$
1%
0&
#3
1$
#4
0$
1+
1(
1"
#5
0(
1'
0*
1!
1$
#6
0$
0+
0'
0)
1#
0"
#7
1*
0!
1$
#8
0$
1+
1(
1"
#9
0+
0(
0*
1!
1$
#10
0$
1+
1'
1)
0#
0"
