EJERCICIO 5/ejercicio5.v
module ROM(input wire[6:0] A, output reg[12:0] Y);
  always @ ( * ) begin
    casex(A)
      7'bxxxxxx0:	Y = 13'b1000000001000;
			7'b00001x1: Y = 13'b0100000001000;
			7'b00000x1: Y = 13'b1000000001000;
			7'b00011x1: Y = 13'b1000000001000;
			7'b00010x1: Y = 13'b0100000001000;
			7'b0010xx1: Y = 13'b0001001000010;
			7'b0011xx1: Y = 13'b1001001100000;
			7'b0100xx1: Y = 13'b0011010000010;
			7'b0101xx1: Y = 13'b0011010000100;
			7'b0110xx1: Y = 13'b1011010100000;
			7'b0111xx1: Y = 13'b1000000111000;
			7'b1000x11: Y = 13'b0100000001000;
			7'b1000x01: Y = 13'b1000000001000;
			7'b1001x11: Y = 13'b1000000001000;
			7'b1001x01: Y = 13'b0100000001000;
			7'b1010xx1: Y = 13'b0011011000010;
			7'b1011xx1: Y = 13'b1011011100000;
			7'b1100xx1: Y = 13'b0100000001000;
			7'b1101xx1: Y = 13'b0000000001001;
			7'b1110xx1: Y = 13'b0011100000010;
			7'b1111xx1: Y = 13'b1011100100000;
			default : Y = 13'b1000000001000;
    endcase
  end
endmodule

EJERCICIO 5/ejercicio5_tb.v
module testbench();
reg[6:0] A;
wire[12:0] Y;
ROM U1(A, Y);

initial begin
  $display("ROM");
  $display(" A | Y");
  $display("-----------|---------");
  $monitor("%b |  %b", A, Y);

  #1  A = 7'b0000000;
  #1  A = 7'b00001x1;
  #1  A = 7'b00000x1;
  #1  A = 7'b00011x1;
  #1  A = 7'b00010x1;
  #1  A = 7'b0010xx1;
  #1  A = 7'b0011xx1;
  #1  A = 7'b0100xx1;
  #1  A = 7'b0101xx1;
  #1  A = 7'b0110xx1;
  #1  A = 7'b0111xx1;
  #1  A = 7'b1000x11;
  #1  A = 7'b1000x01;
  #1  A = 7'b1001x11;
  #1  A = 7'b1001x01;
  #1  A = 7'b1010xx1;
  #1  A = 7'b1011xx1;
  #1  A = 7'b1100xx1;
  #1  A = 7'b1101xx1;
  #1  A = 7'b1110xx1;
  #1  A = 7'b1111111;
  #1  A = 7'b1010110;
  #1  A = 7'b1011011;
  #1  A = 7'b1000100;
  #1  A = 7'b1010101;
  #1  A = 7'b1101110;

end

initial
#30 $finish;
initial begin
  $dumpfile("ejercicio5_tb.vcd");
  $dumpvars(0, testbench);
end
endmodule

EJERCICIO 5/ejercicio5_tb.vcd
$date
	Sat Oct 31 03:07:10 2020
$end
$version
	Icarus Verilog
$end
$timescale
	1ps
$end
$scope module testbench $end
$var wire 13 ! Y [12:0] $end
$var reg 7 " A [6:0] $end
$scope module U1 $end
$var wire 7 # A [6:0] $end
$var reg 13 $ Y [12:0] $end
$upscope $end
$upscope $end
$enddefinitions $end
#0
$dumpvars
bx $
bx #
bx "
bx !
$end
#1
b1000000001000 !
b1000000001000 $
b0 "
b0 #
#2
b100000001000 !
b100000001000 $
b1x1 "
b1x1 #
#3
b1000000001000 !
b1000000001000 $
b0x1 "
b0x1 #
#4
b11x1 "
b11x1 #
#5
b100000001000 !
b100000001000 $
b10x1 "
b10x1 #
#6
b1001000010 !
b1001000010 $
b10xx1 "
b10xx1 #
#7
b1001001100000 !
b1001001100000 $
b11xx1 "
b11xx1 #
#8
b11010000010 !
b11010000010 $
b100xx1 "
b100xx1 #
#9
b11010000100 !
b11010000100 $
b101xx1 "
b101xx1 #
#10
b1011010100000 !
b1011010100000 $
b110xx1 "
b110xx1 #
#11
b1000000111000 !
b1000000111000 $
b111xx1 "
b111xx1 #
#12
b100000001000 !
b100000001000 $
b1000x11 "
b1000x11 #
#13
b1000000001000 !
b1000000001000 $
b1000x01 "
b1000x01 #
#14
b1001x11 "
b1001x11 #
#15
b100000001000 !
b100000001000 $
b1001x01 "
b1001x01 #
#16
b11011000010 !
b11011000010 $
b1010xx1 "
b1010xx1 #
#17
b1011011100000 !
b1011011100000 $
b1011xx1 "
b1011xx1 #
#18
b100000001000 !
b100000001000 $
b1100xx1 "
b1100xx1 #
#19
b1001 !
b1001 $
b1101xx1 "
b1101xx1 #
#20
b11100000010 !
b11100000010 $
b1110xx1 "
b1110xx1 #
#21
b1011100100000 !
b1011100100000 $
b1111111 "
b1111111 #
#22
b1000000001000 !
b1000000001000 $
b1010110 "
b1010110 #
#23
b1011011100000 !
b1011011100000 $
b1011011 "
b1011011 #
#24
b1000000001000 !
b1000000001000 $
b1000100 "
b1000100 #
#25
b11011000010 !
b11011000010 $
b1010101 "
b1010101 #
#26
b1000000001000 !
b1000000001000 $
b1101110 "
b1101110 #
