EJERCICIO 2/ejercicio2.v
module FFP1(input wire clk, reset, enable, A, output reg Y);
 always @ (posedge clk or posedge reset) begin
    if (reset)
      Y <= 1'b0;
    else if(enable)
      Y <= A;
  end
endmodule

module FFPT(input wire clk, reset, enable, A, output wire Y);
  FFP1 U1(clk, reset, enable, ~Y, Y);
endmodule

EJERCICIO 2/ejercicio2_tb.v
module testbench();
reg clk, reset, enable, A;
wire Y;
FFPT U1(clk, reset, enable, A, Y);

always
  #1 clk <= ~clk;

initial begin
  $display("FLIP FLOP TIPO T");
  $display("clk reset, enable A | Y");
  $display("-----------|---------");
  $monitor("%b %b %b %b |  %b", clk, reset, enable, A, Y);
    clk = 0; reset = 0; enable = 0; A = 0;
  #1 clk = 0; reset = 1; enable = 0; A = 0;
  #1 reset = 0; enable = 0; A = 0;
  #1 reset = 0; enable = 0; A = 0;
  #1 reset = 0; enable = 1; A = 0;
  #1 reset = 0; enable = 1; A = 1;
  #1 reset = 0; enable = 1; A = 1;
  #1 reset = 0; enable = 1; A = 1;
  #1 reset = 0; enable = 0; A = 1;
  #1 reset = 0; enable = 0; A = 0;
  #1 reset = 0; enable = 0; A = 0;
  #1 reset = 0; enable = 1; A = 1;
  #1 reset = 0; enable = 1; A = 1;
  #1 reset = 0; enable = 1; A = 1;
  #1 reset = 0; enable = 1; A = 1;
end

initial
#18 $finish;
initial begin
  $dumpfile("ejercicio2_tb.vcd");
  $dumpvars(0, testbench);
end
endmodule

EJERCICIO 2/ejercicio_tb.vcd
$date
	Fri Oct 30 23:07:56 2020
$end
$version
	Icarus Verilog
$end
$timescale
	1ps
$end
$scope module testbench $end
$var wire 1 ! Y $end
$var reg 1 " A $end
$var reg 1 # clk $end
$var reg 1 $ enable $end
$var reg 1 % reset $end
$scope module U1 $end
$var wire 1 " A $end
$var wire 1 # clk $end
$var wire 1 $ enable $end
$var wire 1 % reset $end
$var wire 1 ! Y $end
$scope module U1 $end
$var wire 1 & A $end
$var wire 1 # clk $end
$var wire 1 $ enable $end
$var wire 1 % reset $end
$var reg 1 ! Y $end
$upscope $end
$upscope $end
$upscope $end
$enddefinitions $end
#0
$dumpvars
x&
0%
0$
0#
0"
x!
$end
#1
1&
0!
1#
1%
#2
0#
0%
#3
1#
#4
0#
1$
#5
0&
1!
1#
1"
#6
0#
#7
1&
0!
1#
#8
0#
0$
#9
1#
0"
#10
0#
#11
0&
1!
1#
1"
1$
#12
0#
#13
1&
0!
1#
#14
0#
#15
0&
1!
1#
#16
0#
#17
1&
0!
1#
