EJERCICIO 1/ejercicio1.v
module FFP1(input wire clk, reset, enable, A, output reg Y);
 always @ (posedge clk or posedge reset) begin
    if (reset)
      Y <= 1'b0;
    else if(enable)
      Y <= A;
  end
endmodule

module FFP2(input wire clk, reset, enable,input wire[1:0] A, output wire[1:0] Y);
  FFP1 F1(clk, reset, enable, A[0], Y[0]);
  FFP1 F2(clk, reset, enable, A[1], Y[1]);
endmodule

module FFP4(input wire clk, reset, enable,input wire[3:0] A, output wire[3:0] Y);
  FFP1 F3(clk, reset, enable, A[0], Y[0]);
  FFP1 F4(clk, reset, enable, A[1], Y[1]);
  FFP1 F5(clk, reset, enable, A[2], Y[2]);
  FFP1 F6(clk, reset, enable, A[3], Y[3]);
endmodule

EJERCICIO 1/ejercicio_tb.v
module testbench();
reg clk, reset, enable, A;
reg[1:0]A1;
reg[3:0]A2;
wire Y;
wire[1:0] Y1;
wire[3:0] Y2;

FFP1 U1(clk, reset, enable, A, Y);
FFP2 U2(clk, reset, enable, A1, Y1);
FFP4 U3(clk, reset, enable, A2, Y2);

always
  #1 clk <= ~clk;

initial begin
  $display("FLIP FLOP 1");
  $display("clk reset, enable A | Y");
  $display("-----------|---------");
  $monitor("%b %b %b %b |  %b", clk, reset, enable, A, Y);
    clk = 0; reset = 0; enable = 0; A = 0;
  #1 clk = 0; reset = 1; enable = 0; A = 0;
  #1 reset = 0; enable = 0; A = 0;
  #1 reset = 0; enable = 0; A = 0;
  #1 reset = 0; enable = 1; A = 0;
  #1 reset = 0; enable = 1; A = 1;
  #1 reset = 0; enable = 1; A = 1;
  #1 reset = 0; enable = 1; A = 1;
  #1 reset = 0; enable = 0; A = 1;
  #1 reset = 0; enable = 0; A = 0;
  #1 reset = 0; enable = 0; A = 0;
end

initial begin
  #12
  $display("");
  $display("FLIP FLOP 2");
  $display("clk reset, enable A | Y");
  $display("-----------|---------");
  $monitor("%b %b %b %b |  %b", clk, reset, enable, A1, Y1);
      clk = 0; reset = 0; enable = 0; A1 = 00;
    #1 reset = 1; enable = 0; A1 =00;
    #1 reset = 0; enable = 0; A1 = 00;
    #1 reset = 0; enable = 0; A1 = 00;
    #1 reset = 0; enable = 1; A1 = 00;
    #1 reset = 0; enable = 1; A1 = 01;
    #1 reset = 0; enable = 1; A1 = 01;
    #1 reset = 0; enable = 1; A1 = 10;
    #1 reset = 0; enable = 1; A1 = 10;
    #1 reset = 0; enable = 1; A1 = 11;
  end

  initial begin
    #23
    $display("");
    $display("FLIP FLOP 4");
    $display("clk reset, enable A | Y");
    $display("-----------|---------");
    $monitor("%b %b %b %b |  %b", clk, reset, enable, A2, Y2);
        clk = 0; reset = 0; enable = 0; A2 = 0000;
      #1 reset = 1; enable = 0; A2 =0000;
      #1 reset = 0; enable = 0; A2 = 0000;
      #1 reset = 0; enable = 0; A2 = 0000;
      #1 reset = 0; enable = 1; A2 = 0000;
      #1 reset = 0; enable = 1; A2 = 0001;
      #1 reset = 0; enable = 1; A2 = 0001;
      #1 reset = 0; enable = 1; A2 = 0010;
      #1 reset = 0; enable = 1; A2 = 0010;
      #1 reset = 0; enable = 1; A2 = 0011;
      #1 reset = 0; enable = 1; A2 = 0011;
      #1 reset = 0; enable = 1; A2 = 0100;
      #1 reset = 0; enable = 1; A2 = 0100;
      #1 reset = 0; enable = 1; A2 = 0101;
      #1 reset = 0; enable = 1; A2 = 0101;

    end

  initial
  #40 $finish;
initial begin
    $dumpfile("ejercicio_tb.vcd");
    $dumpvars(0, testbench);
  end
endmodule

EJERCICIO 1/ejercicio_tb.vcd
$date
	Sat Oct 31 02:49:03 2020
$end
$version
	Icarus Verilog
$end
$timescale
	1ps
$end
$scope module testbench $end
$var wire 4 ! Y2 [3:0] $end
$var wire 2 " Y1 [1:0] $end
$var wire 1 # Y $end
$var reg 1 $ A $end
$var reg 2 % A1 [1:0] $end
$var reg 4 & A2 [3:0] $end
$var reg 1 ' clk $end
$var reg 1 ( enable $end
$var reg 1 ) reset $end
$scope module U1 $end
$var wire 1 $ A $end
$var wire 1 ' clk $end
$var wire 1 ( enable $end
$var wire 1 ) reset $end
$var reg 1 # Y $end
$upscope $end
$scope module U2 $end
$var wire 2 * A [1:0] $end
$var wire 1 ' clk $end
$var wire 1 ( enable $end
$var wire 1 ) reset $end
$var wire 2 + Y [1:0] $end
$scope module F1 $end
$var wire 1 , A $end
$var wire 1 ' clk $end
$var wire 1 ( enable $end
$var wire 1 ) reset $end
$var reg 1 - Y $end
$upscope $end
$scope module F2 $end
$var wire 1 . A $end
$var wire 1 ' clk $end
$var wire 1 ( enable $end
$var wire 1 ) reset $end
$var reg 1 / Y $end
$upscope $end
$upscope $end
$scope module U3 $end
$var wire 4 0 A [3:0] $end
$var wire 1 ' clk $end
$var wire 1 ( enable $end
$var wire 1 ) reset $end
$var wire 4 1 Y [3:0] $end
$scope module F3 $end
$var wire 1 2 A $end
$var wire 1 ' clk $end
$var wire 1 ( enable $end
$var wire 1 ) reset $end
$var reg 1 3 Y $end
$upscope $end
$scope module F4 $end
$var wire 1 4 A $end
$var wire 1 ' clk $end
$var wire 1 ( enable $end
$var wire 1 ) reset $end
$var reg 1 5 Y $end
$upscope $end
$scope module F5 $end
$var wire 1 6 A $end
$var wire 1 ' clk $end
$var wire 1 ( enable $end
$var wire 1 ) reset $end
$var reg 1 7 Y $end
$upscope $end
$scope module F6 $end
$var wire 1 8 A $end
$var wire 1 ' clk $end
$var wire 1 ( enable $end
$var wire 1 ) reset $end
$var reg 1 9 Y $end
$upscope $end
$upscope $end
$upscope $end
$enddefinitions $end
#0
$dumpvars
x9
x8
x7
x6
x5
x4
x3
x2
bx 1
bx 0
x/
x.
x-
x,
bx +
bx *
0)
0(
0'
bx &
bx %
0$
x#
bx "
bx !
$end
#1
0#
0-
b0 "
b0 +
0/
03
05
07
b0 !
b0 1
09
1'
1)
#2
0'
0)
#3
1'
#4
0'
1(
#5
x9
x7
x5
bx !
bx 1
x3
x/
bx "
bx +
x-
1#
1'
1$
#6
0'
#7
1'
#8
0'
0(
#9
1'
0$
#10
0'
#11
1'
#12
0,
0.
b0 %
b0 *
1'
#13
0#
0-
b0 "
b0 +
0/
03
05
07
b0 !
b0 1
09
0'
1)
#14
1'
0)
#15
0'
#16
x3
x5
x7
bx !
bx 1
x9
1'
1(
#17
0'
1,
b1 %
b1 *
#18
b1 "
b1 +
1-
1'
#19
0'
0,
1.
b10 %
b10 *
#20
0-
b10 "
b10 +
1/
1'
#21
0'
1,
b11 %
b11 *
#22
b11 "
b11 +
1-
1'
#23
02
04
06
08
b0 &
b0 0
0(
1'
#24
09
07
05
b0 !
b0 1
03
0/
b0 "
b0 +
0-
0'
1)
#25
1'
0)
#26
0'
#27
1/
b11 "
b11 +
1-
1'
1(
#28
0'
12
b1 &
b1 0
#29
b1 !
b1 1
13
1'
#30
0'
02
14
18
b1010 &
b1010 0
#31
19
15
b1010 !
b1010 1
03
1'
#32
0'
12
b1011 &
b1011 0
#33
b1011 !
b1011 1
13
1'
#34
0'
02
04
16
08
b100 &
b100 0
#35
09
17
05
b100 !
b100 1
03
1'
#36
0'
12
b101 &
b101 0
#37
b101 !
b101 1
13
1'
